djai/__init__.py
djai/cli.py
djai/spotify.py
djai-0.4.0.dist-info/METADATA
djai-0.4.0.dist-info/WHEEL
djai-0.4.0.dist-info/entry_points.txt
djai-0.4.0.dist-info/licenses/LICENSE
djai-0.4.0.dist-info/RECORD
