Metadata-Version: 2.4
Name: djai
Version: 0.4.0
Summary: DJ AI Ideation Tools.
Project-URL: Homepage, https://github.com/8W9aG/djai
Project-URL: Repository, https://github.com/8W9aG/djai
Project-URL: Issues, https://github.com/8W9aG/djai/issues
Author-email: Your Name <you@example.com>
License: MIT License
License-File: LICENSE
Classifier: License :: OSI Approved :: MIT License
Classifier: Operating System :: OS Independent
Classifier: Programming Language :: Python :: 3
Classifier: Programming Language :: Python :: 3.9
Classifier: Programming Language :: Python :: 3.10
Classifier: Programming Language :: Python :: 3.11
Classifier: Programming Language :: Python :: 3.12
Requires-Python: >=3.9
Requires-Dist: demucs>=4.0.0
Requires-Dist: diffq>=0.2.4
Requires-Dist: python-dotenv>=1.0.0
Requires-Dist: requests>=2.31.0
Requires-Dist: torch>=2.3.0
Requires-Dist: torchaudio>=2.3.0
Requires-Dist: torchcodec>=0.2.0
Requires-Dist: yt-dlp>=2024.10.22
Provides-Extra: dev
Requires-Dist: pytest>=7.4; extra == 'dev'
Requires-Dist: ruff>=0.5.0; extra == 'dev'
